unified_fs/__init__.py
unified_fs/config/file_extension_mapping.yaml
unified_fs/file_system.py
unified_fs/operations.py
unified_fs/readers/__init__.py
unified_fs/readers/text_readers.py
unified_fs-0.0.1.dist-info/LICENSE
unified_fs-0.0.1.dist-info/METADATA
unified_fs-0.0.1.dist-info/WHEEL
unified_fs-0.0.1.dist-info/entry_points.txt
unified_fs-0.0.1.dist-info/RECORD
