Metadata-Version: 2.1
Name: unified_fs
Version: 0.0.1
Summary: unified_fs
License: MIT
Author: Balakrishna Maduru
Author-email: balakrishnamaduru@gmail.com
Requires-Python: >=3.10,<4.0
Classifier: License :: OSI Approved :: MIT License
Classifier: Programming Language :: Python :: 3
Classifier: Programming Language :: Python :: 3.10
Classifier: Programming Language :: Python :: 3.11
Classifier: Programming Language :: Python :: 3.12
Requires-Dist: autopep8 (>=2.0.4,<3.0.0)
Requires-Dist: fsspec (>=2024.2.0,<2025.0.0)
Requires-Dist: pytest (>=8.0.1,<9.0.0)
Requires-Dist: pyyaml (>=6.0.1,<7.0.0)
Requires-Dist: s3fs (>=2024.2.0,<2025.0.0)
